setup.py
asdf_distributions/Binomialdistribution.py
asdf_distributions/Gaussiandistribution.py
asdf_distributions/Generaldistribution.py
asdf_distributions/__init__.py
asdf_distributions.egg-info/PKG-INFO
asdf_distributions.egg-info/SOURCES.txt
asdf_distributions.egg-info/dependency_links.txt
asdf_distributions.egg-info/not-zip-safe
asdf_distributions.egg-info/top_level.txt