Metadata-Version: 1.0
Name: asdf-distributions
Version: 0.1
Summary: Gaussian and Binomial distributions
Home-page: UNKNOWN
Author: Felipe C
Author-email: UNKNOWN
License: UNKNOWN
Platform: UNKNOWN
